HexColor/__init__.py
hexcolor-1.0.0.dist-info/LICENSE
hexcolor-1.0.0.dist-info/METADATA
hexcolor-1.0.0.dist-info/WHEEL
hexcolor-1.0.0.dist-info/RECORD
